randflake/__init__.py
randflake/randflake.py
randflake/sparx64.py
randflake/test_package.py
randflake/test_randflake.py
randflake/test_sparx64.py
randflake-1.7.1.dist-info/METADATA
randflake-1.7.1.dist-info/WHEEL
randflake-1.7.1.dist-info/licenses/LICENSE
randflake-1.7.1.dist-info/RECORD
