Metadata-Version: 2.4
Name: randflake
Version: 1.7.1
Summary: A Python implementation the Randflake ID: a distributed, uniform, unpredictable, unique random ID generator.
Project-URL: Repository, https://github.com/gosuda/randflake
Project-URL: Issues, https://github.com/gosuda/randflake/issues
Project-URL: Homepage, https://gosuda.org/randflake
Author: GoSuda
License: MIT License
License-File: LICENSE
Classifier: Development Status :: 3 - Alpha
Classifier: Intended Audience :: Developers
Classifier: License :: OSI Approved :: MIT License
Classifier: Programming Language :: Python :: 3
Classifier: Programming Language :: Python :: 3.7
Classifier: Programming Language :: Python :: 3.8
Classifier: Programming Language :: Python :: 3.9
Classifier: Programming Language :: Python :: 3.10
Classifier: Programming Language :: Python :: 3.11
Classifier: Topic :: Security :: Cryptography
Requires-Python: >=3.7
